{"commitInfo":{"timestamp":1781612159296,"operation":"WRITE","operationParameters":{"mode":"Append","partitionBy":"[\"date\"]"},"readVersion":248,"isolationLevel":"Serializable","isBlindAppend":true,"operationMetrics":{"numFiles":"5","numOutputRows":"5","numOutputBytes":"12704"},"engineInfo":"Apache-Spark/3.4.4 Delta-Lake/2.4.0","txnId":"2ad48da3-d83f-4918-9df7-831ffe74e1ad"}}
{"add":{"path":"date=2131-05-26/part-00002-e473c913-23dd-4530-afe4-e370c0e08643.c000.snappy.parquet","partitionValues":{"date":"2131-05-26"},"size":2541,"modificationTime":1781612159279,"dataChange":true,"stats":"{\"numRecords\":1,\"minValues\":{\"subject_id\":10038999,\"hadm_id\":27189241,\"stay_id\":39711498,\"charttime\":\"2131-05-26T21:00:00.000+06:00\",\"itemid\":220045,\"value\":95.0,\"valueuom\":\"bpm\",\"storetime\":\"2131-05-26T21:03:00.000+06:00\",\"ingestion_time\":\"2026-06-16T18:15:59.084+06:00\"},\"maxValues\":{\"subject_id\":10038999,\"hadm_id\":27189241,\"stay_id\":39711498,\"charttime\":\"2131-05-26T21:00:00.000+06:00\",\"itemid\":220045,\"value\":95.0,\"valueuom\":\"bpm\",\"storetime\":\"2131-05-26T21:03:00.000+06:00\",\"ingestion_time\":\"2026-06-16T18:15:59.084+06:00\"},\"nullCount\":{\"subject_id\":0,\"hadm_id\":0,\"stay_id\":0,\"charttime\":0,\"itemid\":0,\"value\":0,\"valueuom\":0,\"storetime\":0,\"ingestion_time\":0}}"}}
{"add":{"path":"date=2131-05-26/part-00004-e4fc1b6b-2e1e-489b-bdc4-13cf7c17feb4.c000.snappy.parquet","partitionValues":{"date":"2131-05-26"},"size":2541,"modificationTime":1781612159279,"dataChange":true,"stats":"{\"numRecords\":1,\"minValues\":{\"subject_id\":10038999,\"hadm_id\":27189241,\"stay_id\":39711498,\"charttime\":\"2131-05-26T22:00:00.000+06:00\",\"itemid\":220045,\"value\":98.0,\"valueuom\":\"bpm\",\"storetime\":\"2131-05-26T22:20:00.000+06:00\",\"ingestion_time\":\"2026-06-16T18:15:59.084+06:00\"},\"maxValues\":{\"subject_id\":10038999,\"hadm_id\":27189241,\"stay_id\":39711498,\"charttime\":\"2131-05-26T22:00:00.000+06:00\",\"itemid\":220045,\"value\":98.0,\"valueuom\":\"bpm\",\"storetime\":\"2131-05-26T22:20:00.000+06:00\",\"ingestion_time\":\"2026-06-16T18:15:59.084+06:00\"},\"nullCount\":{\"subject_id\":0,\"hadm_id\":0,\"stay_id\":0,\"charttime\":0,\"itemid\":0,\"value\":0,\"valueuom\":0,\"storetime\":0,\"ingestion_time\":0}}"}}
{"add":{"path":"date=2131-05-26/part-00007-41adda5c-9f7b-4235-bb93-114c33263d38.c000.snappy.parquet","partitionValues":{"date":"2131-05-26"},"size":2541,"modificationTime":1781612159291,"dataChange":true,"stats":"{\"numRecords\":1,\"minValues\":{\"subject_id\":10038999,\"hadm_id\":27189241,\"stay_id\":39711498,\"charttime\":\"2131-05-26T23:00:00.000+06:00\",\"itemid\":220045,\"value\":114.0,\"valueuom\":\"bpm\",\"storetime\":\"2131-05-27T02:19:00.000+06:00\",\"ingestion_time\":\"2026-06-16T18:15:59.084+06:00\"},\"maxValues\":{\"subject_id\":10038999,\"hadm_id\":27189241,\"stay_id\":39711498,\"charttime\":\"2131-05-26T23:00:00.000+06:00\",\"itemid\":220045,\"value\":114.0,\"valueuom\":\"bpm\",\"storetime\":\"2131-05-27T02:19:00.000+06:00\",\"ingestion_time\":\"2026-06-16T18:15:59.084+06:00\"},\"nullCount\":{\"subject_id\":0,\"hadm_id\":0,\"stay_id\":0,\"charttime\":0,\"itemid\":0,\"value\":0,\"valueuom\":0,\"storetime\":0,\"ingestion_time\":0}}"}}
{"add":{"path":"date=2131-05-27/part-00009-dfae3df3-b0e5-4453-9228-3853ff17ac72.c000.snappy.parquet","partitionValues":{"date":"2131-05-27"},"size":2541,"modificationTime":1781612159279,"dataChange":true,"stats":"{\"numRecords\":1,\"minValues\":{\"subject_id\":10038999,\"hadm_id\":27189241,\"stay_id\":39711498,\"charttime\":\"2131-05-27T00:00:00.000+06:00\",\"itemid\":220045,\"value\":123.0,\"valueuom\":\"bpm\",\"storetime\":\"2131-05-27T02:19:00.000+06:00\",\"ingestion_time\":\"2026-06-16T18:15:59.084+06:00\"},\"maxValues\":{\"subject_id\":10038999,\"hadm_id\":27189241,\"stay_id\":39711498,\"charttime\":\"2131-05-27T00:00:00.000+06:00\",\"itemid\":220045,\"value\":123.0,\"valueuom\":\"bpm\",\"storetime\":\"2131-05-27T02:19:00.000+06:00\",\"ingestion_time\":\"2026-06-16T18:15:59.084+06:00\"},\"nullCount\":{\"subject_id\":0,\"hadm_id\":0,\"stay_id\":0,\"charttime\":0,\"itemid\":0,\"value\":0,\"valueuom\":0,\"storetime\":0,\"ingestion_time\":0}}"}}
{"add":{"path":"date=2131-05-27/part-00011-2d2a9c3c-58a3-43ea-b616-5abe8be1e657.c000.snappy.parquet","partitionValues":{"date":"2131-05-27"},"size":2540,"modificationTime":1781612159287,"dataChange":true,"stats":"{\"numRecords\":1,\"minValues\":{\"subject_id\":10038999,\"hadm_id\":27189241,\"stay_id\":39711498,\"charttime\":\"2131-05-27T01:00:00.000+06:00\",\"itemid\":220045,\"value\":119.0,\"valueuom\":\"bpm\",\"storetime\":\"2131-05-27T02:19:00.000+06:00\",\"ingestion_time\":\"2026-06-16T18:15:59.084+06:00\"},\"maxValues\":{\"subject_id\":10038999,\"hadm_id\":27189241,\"stay_id\":39711498,\"charttime\":\"2131-05-27T01:00:00.000+06:00\",\"itemid\":220045,\"value\":119.0,\"valueuom\":\"bpm\",\"storetime\":\"2131-05-27T02:19:00.000+06:00\",\"ingestion_time\":\"2026-06-16T18:15:59.084+06:00\"},\"nullCount\":{\"subject_id\":0,\"hadm_id\":0,\"stay_id\":0,\"charttime\":0,\"itemid\":0,\"value\":0,\"valueuom\":0,\"storetime\":0,\"ingestion_time\":0}}"}}
